{
    "LONG": {
        "context": {
            "tickers": [
                "AAPL"
            ],
            "execution_timeframe": "1h",
            "data_timeframes": [
                "1h"
            ],
            "dateframe": {
                "start": "2024-02-02",
                "end": "2024-12-28"
            }
        },
        "OPEN": {
            "CONDITIONS": {
                "left": {
                    "func": "RSI",
                    "arg": {
                        "period": 14,
                        "timeframe": "1h",
                        "offset": 0
                    }
                },
                "operator": ">",
                "right": {
                    "value": 35
                }
            },
            "ARGUMENTS": {
                "stopLossPercent": 100,
                "takeProfitPercent": 100,
                "initialOpenPositionInvestType": "percentCashBalance",
                "initialOpenPositionInvestAmount": 0.2,
                "recurring": false,
                "recurringPeriod": 5,
                "recurringInvestType": "percentCashBalance",
                "recurringInvestAmount": 0.1,
                "maxRecurringCount": 0
            }
        },
        "CLOSE": {
            "CONDITIONS": {
                "left": {
                    "func": "SMA",
                    "arg": {
                        "period": 14,
                        "timeframe": "1h",
                        "offset": 0
                    }
                },
                "operator": "<",
                "right": {
                    "value": 75
                }
            },
            "ARGUMENTS": {
                "test": 0.5
            }
        }
    }
}